flask_signature_auth/__init__.py
flask_signature_auth-1.0.0.dist-info/LICENSE
flask_signature_auth-1.0.0.dist-info/METADATA
flask_signature_auth-1.0.0.dist-info/WHEEL
flask_signature_auth-1.0.0.dist-info/top_level.txt
flask_signature_auth-1.0.0.dist-info/RECORD
