Metadata-Version: 2.1
Name: flask-signature-auth
Version: 1.0.0
Summary: UNKNOWN
Home-page: https://github.com/kunyo/flask_signature_auth
Author: Stefano Cocchi
Author-email: UNKNOWN
License: BSD 3-Clause License
Platform: MacOS X
Platform: Posix
Classifier: Intended Audience :: Developers
Classifier: License :: OSI Approved :: BSD License
Classifier: Operating System :: MacOS :: MacOS X
Classifier: Operating System :: POSIX
Classifier: Programming Language :: Python
Classifier: Programming Language :: Python :: 3.7
Classifier: Programming Language :: Python :: 3.8
Classifier: Development Status :: 5 - Production/Stable
Classifier: Topic :: Software Development :: Libraries :: Python Modules
Requires-Dist: Flask (>=1.1.2)
Requires-Dist: cryptography
Requires-Dist: jwcrypto
